comparecast/__init__.py
comparecast/cgfs.py
comparecast/comparecast.py
comparecast/confint.py
comparecast/confseq.py
comparecast/diagnostics.py
comparecast/eprocess.py
comparecast/forecasters.py
comparecast/kernels.py
comparecast/plotting.py
comparecast/scoring.py
comparecast/utils.py
comparecast/data_utils/__init__.py
comparecast/data_utils/baseball.py
comparecast/data_utils/synthetic.py
comparecast/data_utils/weather.py
comparecast-1.0.0.dist-info/LICENSE.txt
comparecast-1.0.0.dist-info/METADATA
comparecast-1.0.0.dist-info/WHEEL
comparecast-1.0.0.dist-info/top_level.txt
comparecast-1.0.0.dist-info/RECORD
