Metadata-Version: 2.1
Name: comparecast
Version: 1.0.0
Summary: Comparing Sequential Forecasters
Home-page: https://github.com/yjchoe/ComparingForecasters
Author: Yo Joong Choe, Aaditya Ramdas
Author-email: yjchoe@uchicago.edu
License: MIT
Requires-Python: >=3.7
License-File: LICENSE.txt
Requires-Dist: numpy >=1.20
Requires-Dist: scipy
Requires-Dist: pandas >=1.0
Requires-Dist: seaborn >=0.11
Requires-Dist: tqdm
Requires-Dist: openpyxl
Requires-Dist: confseq >=0.0.9
